saturnscrape/__init__.py
saturnscrape/__main__.py
saturnscrape/client.py
saturnscrape/types.py
saturnscrape/utils.py
saturnscrape-1.2.0.dist-info/entry_points.txt
saturnscrape-1.2.0.dist-info/LICENSE
saturnscrape-1.2.0.dist-info/WHEEL
saturnscrape-1.2.0.dist-info/METADATA
saturnscrape-1.2.0.dist-info/RECORD
