Metadata-Version: 2.1
Name: saturnscrape
Version: 1.2.0
Summary: Scrapes information from https://saturn.live, a collaborate school scheduling system.
Home-page: https://github.com/regulad/saturnscrape
License: GPLv3
Author: Parker Wahle
Author-email: parkeredwardwahle2017@gmail.com
Requires-Python: >=3.10,<4.0
Classifier: License :: Other/Proprietary License
Classifier: Programming Language :: Python :: 3
Classifier: Programming Language :: Python :: 3.10
Requires-Dist: PyJWT[crypto] (>=2.3.0,<3.0.0)
Requires-Dist: aiofiles (>=0.8.0,<0.9.0)
Requires-Dist: aiohttp (>=3.8.1,<4.0.0)
Requires-Dist: arrow (>=0.11,<0.15)
Requires-Dist: ics (>=0.7,<0.8)
Requires-Dist: pytz (>=2022.1,<2023.0)
Requires-Dist: tzlocal (>=4.2,<5.0)
Requires-Dist: vobject (>=0.9.6,<0.10.0)
Project-URL: Repository, https://github.com/regulad/saturnscrape
